yarn_build.py
yarn.build-3.0.0.dist-info/METADATA
yarn.build-3.0.0.dist-info/WHEEL
yarn.build-3.0.0.dist-info/entry_points.txt
yarn.build-3.0.0.dist-info/top_level.txt
yarn.build-3.0.0.dist-info/RECORD
