Metadata-Version: 2.1
Name: yarn.build
Version: 3.0.0
Summary: Build JS artifacts with yarn
Home-page: https://github.com/gforcada/yarn.build
Author: Gil Forcada Codinachs
Author-email: gil.gnome@gmail.com
License: GPL version 3
Keywords: yarn javascript compile build release zest.releaser
Classifier: Development Status :: 5 - Production/Stable
Classifier: Environment :: Plugins
Classifier: Intended Audience :: Developers
Classifier: License :: OSI Approved :: GNU General Public License v3 or later (GPLv3+)
Classifier: Programming Language :: Python
Classifier: Programming Language :: Python :: 3
Classifier: Programming Language :: Python :: 3.11
Classifier: Topic :: Software Development :: Build Tools
Requires-Python: >=3.11
Requires-Dist: setuptools
Requires-Dist: zest.releaser
